textplumber/__init__.py
textplumber/_modidx.py
textplumber/chars.py
textplumber/clean.py
textplumber/core.py
textplumber/embeddings.py
textplumber/lexicons.py
textplumber/pos.py
textplumber/preprocess.py
textplumber/report.py
textplumber/store.py
textplumber/textstats.py
textplumber/tokens.py
textplumber/vader.py
textplumber-0.0.11.dist-info/LICENSE
textplumber-0.0.11.dist-info/METADATA
textplumber-0.0.11.dist-info/WHEEL
textplumber-0.0.11.dist-info/entry_points.txt
textplumber-0.0.11.dist-info/top_level.txt
textplumber-0.0.11.dist-info/RECORD
