Metadata-Version: 2.2
Name: textplumber
Version: 0.0.11
Summary: Pipeline components for Sci-kit learn to extract relevant features from text data, including tokens, parts of speech, lexicon scores, document-level statistics and embeddings.
Home-page: https://github.com/polsci/textplumber
Author: Geoff Ford
Author-email: geoffrey.ford@canterbury.ac.nz
License: Apache Software License 2.0
Keywords: nbdev jupyter notebook python
Classifier: Development Status :: 4 - Beta
Classifier: Intended Audience :: Developers
Classifier: Natural Language :: English
Classifier: Programming Language :: Python :: 3.9
Classifier: Programming Language :: Python :: 3.10
Classifier: Programming Language :: Python :: 3.11
Classifier: Programming Language :: Python :: 3.12
Classifier: License :: OSI Approved :: Apache Software License
Requires-Python: >=3.9
License-File: LICENSE
Requires-Dist: spacy
Requires-Dist: model2vec
Requires-Dist: scikit-learn
Requires-Dist: lxml
Requires-Dist: textstat
Requires-Dist: pandas
Requires-Dist: matplotlib
Requires-Dist: seaborn
Requires-Dist: nltk
Requires-Dist: imbalanced-learn
Requires-Dist: supertree
Requires-Dist: datasets
Requires-Dist: fastcore
Requires-Dist: vaderSentiment
Requires-Dist: wordcloud
Provides-Extra: dev
Requires-Dist: jupyterlab; extra == "dev"
Requires-Dist: nbdev; extra == "dev"
Requires-Dist: jupyterlab-quarto; extra == "dev"
Requires-Dist: twine; extra == "dev"
Dynamic: author
Dynamic: author-email
Dynamic: classifier
Dynamic: description
Dynamic: description-content-type
Dynamic: home-page
Dynamic: keywords
Dynamic: license
Dynamic: provides-extra
Dynamic: requires-dist
Dynamic: requires-python
Dynamic: summary
